cthulhucrypt/__init__.py
cthulhucrypt/cli.py
cthulhucrypt/core.py
cthulhucrypt-0.2.7.dist-info/licenses/LICENSE
cthulhucrypt-0.2.7.dist-info/METADATA
cthulhucrypt-0.2.7.dist-info/WHEEL
cthulhucrypt-0.2.7.dist-info/entry_points.txt
cthulhucrypt-0.2.7.dist-info/top_level.txt
cthulhucrypt-0.2.7.dist-info/RECORD
