Metadata-Version: 2.4
Name: cthulhucrypt
Version: 0.2.7
Summary: An unholy encryption and hashing algorithm that defies brute force
Author: null
Classifier: Programming Language :: Python :: 3
Classifier: License :: OSI Approved :: MIT License
Classifier: Operating System :: OS Independent
Requires-Python: >=3.6
License-File: LICENSE
Dynamic: author
Dynamic: classifier
Dynamic: description
Dynamic: description-content-type
Dynamic: license-file
Dynamic: requires-python
Dynamic: summary
